devskills/__init__.py
devskills/__main__.py
devskills/cli.py
devskills/main.py
devskills/prompts.py
devskills/skills.py
devskills/bundled_prompts/mcp-builder.md
devskills/bundled_prompts/skill-creator.md
devskills/bundled_skills/__init__.py
devskills/bundled_skills/mcp-builder/SKILL.md
devskills/bundled_skills/mcp-builder/references/evaluation.md
devskills/bundled_skills/mcp-builder/references/mcp_best_practices.md
devskills/bundled_skills/mcp-builder/references/node_mcp_server.md
devskills/bundled_skills/mcp-builder/references/python_mcp_server.md
devskills/bundled_skills/mcp-builder/scripts/connections.py
devskills/bundled_skills/mcp-builder/scripts/evaluation.py
devskills/bundled_skills/mcp-builder/scripts/example_evaluation.xml
devskills/bundled_skills/mcp-builder/scripts/requirements.txt
devskills/bundled_skills/skill-creator/SKILL.md
devskills/bundled_skills/skill-creator/references/output-patterns.md
devskills/bundled_skills/skill-creator/references/workflows.md
devskills/bundled_skills/skill-creator/scripts/init_skill.py
devskills/bundled_skills/skill-creator/scripts/quick_validate.py
devskills-0.2.0.dist-info/METADATA
devskills-0.2.0.dist-info/WHEEL
devskills-0.2.0.dist-info/entry_points.txt
devskills-0.2.0.dist-info/licenses/LICENSE
devskills-0.2.0.dist-info/RECORD
