Metadata-Version: 2.4
Name: devskills
Version: 0.2.0
Summary: MCP server exposing reusable skills for AI coding agents
Project-URL: Homepage, https://github.com/mk0e/devskills
Project-URL: Documentation, https://github.com/mk0e/devskills#readme
Project-URL: Repository, https://github.com/mk0e/devskills
Project-URL: Issues, https://github.com/mk0e/devskills/issues
License-Expression: MIT
License-File: LICENSE
Keywords: ai,claude,coding-agent,copilot,mcp,skills
Classifier: Development Status :: 4 - Beta
Classifier: Intended Audience :: Developers
Classifier: License :: OSI Approved :: MIT License
Classifier: Programming Language :: Python :: 3
Classifier: Programming Language :: Python :: 3.10
Classifier: Programming Language :: Python :: 3.11
Classifier: Programming Language :: Python :: 3.12
Classifier: Topic :: Software Development :: Libraries :: Python Modules
Requires-Python: >=3.10
Requires-Dist: click>=8.0.0
Requires-Dist: mcp>=1.23.0
Requires-Dist: pyyaml>=6.0.2
Provides-Extra: dev
Requires-Dist: pytest-asyncio>=1.3.0; extra == 'dev'
Requires-Dist: pytest>=9.0.2; extra == 'dev'
